__init__.py
main.py
py.typed
flake8_import_guard-1.3.3.data/data/py.typed
flake8_import_guard-1.3.3.dist-info/METADATA
flake8_import_guard-1.3.3.dist-info/WHEEL
flake8_import_guard-1.3.3.dist-info/entry_points.txt
flake8_import_guard-1.3.3.dist-info/licenses/LICENSE
flake8_import_guard-1.3.3.dist-info/RECORD
