Metadata-Version: 2.4
Name: flake8-import-guard
Version: 1.3.3
Summary: Flake8 plugin to enforce import restrictions in Python projects.
Project-URL: Homepage, https://qiita.com/inetcpl
Project-URL: Repository, https://github.com/K-dash/flake8-import-guard
Author-email: K'  <51281148+K-dash@users.noreply.github.com>
License-Expression: MIT
License-File: LICENSE
Keywords: flake8,import,linter,plugin
Classifier: Environment :: Console
Classifier: Framework :: Flake8
Classifier: Intended Audience :: Developers
Classifier: License :: OSI Approved :: MIT License
Classifier: Programming Language :: Python :: 3.9
Classifier: Programming Language :: Python :: 3.10
Classifier: Programming Language :: Python :: 3.11
Classifier: Programming Language :: Python :: 3.12
Classifier: Programming Language :: Python :: 3.13
Classifier: Topic :: Software Development :: Quality Assurance
Requires-Python: <4,>=3.9
Requires-Dist: flake8<8,>=7.1.2
Requires-Dist: gitpython<4,>=3.1.44
Requires-Dist: python-dotenv<2,>=1.1.0
Requires-Dist: toml<0.11,>=0.10.2
